MPDSnCxx_Interface.py
__init__.py
aa_opto_electronic_mpdsncxx_interface-1.0.2.dist-info/licenses/LICENSE
aa_opto_electronic_mpdsncxx_interface-1.0.2.dist-info/METADATA
aa_opto_electronic_mpdsncxx_interface-1.0.2.dist-info/WHEEL
aa_opto_electronic_mpdsncxx_interface-1.0.2.dist-info/top_level.txt
aa_opto_electronic_mpdsncxx_interface-1.0.2.dist-info/RECORD
