Metadata-Version: 2.4
Name: AA-Opto-Electronic-MPDSnCxx-Interface
Version: 1.0.2
Summary: Python package for USB interfacing of the AA Opto-Electronic MPDSnCxx Radio Frequency Driver
Author-email: Edward Appleton <edwardisaaca@gmail.com>
Maintainer-email: Edward Appleton <edwardisaaca@gmail.com>
License-Expression: MIT
Project-URL: Homepage, https://github.com/the-professor510/AA-Opto-Electronic-MPDSnCxx-Interface
Classifier: Development Status :: 4 - Beta
Classifier: Intended Audience :: Developers
Classifier: Topic :: System :: Hardware :: Universal Serial Bus (USB)
Classifier: Topic :: Scientific/Engineering :: Physics
Classifier: Programming Language :: Python
Classifier: Programming Language :: Python :: 3.13
Classifier: Programming Language :: Python :: 3.14
Classifier: Programming Language :: Python :: 3.15
Requires-Python: >=3.13.0
License-File: LICENSE
Requires-Dist: pyserial>=3.5
Dynamic: license-file
